README.rst
setup.py
scripts/run_tkpip.py
tkpip/__init__.py
tkpip/install_pip.py
tkpip/tkpip.py
tkpip.egg-info/PKG-INFO
tkpip.egg-info/SOURCES.txt
tkpip.egg-info/dependency_links.txt
tkpip.egg-info/top_level.txt
tkpip/lib/__init__.py
tkpip/lib/backwardcompat.py
tkpip/lib/cache.py
tkpip/lib/dist.py
tkpip/lib/dump.py
tkpip/lib/listboxdata.py