Metadata-Version: 1.1
Name: tkpip
Version: 0.1.4
Summary: A tool for installing and managing Python packages based on Tk.
Home-page: https://github.com/lishnih/tkpip
Author: Stan
Author-email: lishnih@gmail.com
License: Public Domain
Keywords: tk,pip,pypi
Platform: any
Classifier: Development Status :: 3 - Alpha
Classifier: Intended Audience :: Developers
Classifier: License :: Public Domain
Classifier: Operating System :: OS Independent
Classifier: Programming Language :: Python
Classifier: Programming Language :: Python :: 2.7
Classifier: Programming Language :: Python :: 3.3
Classifier: Topic :: Utilities
